README.md
setup.py
esay_tk_cnblog/__init__.py
esay_tk_cnblog/say_hello.py
esay_tk_cnblog.egg-info/PKG-INFO
esay_tk_cnblog.egg-info/SOURCES.txt
esay_tk_cnblog.egg-info/dependency_links.txt
esay_tk_cnblog.egg-info/top_level.txt