Metadata-Version: 2.1
Name: esay-tk-cnblog
Version: 0.0.1
Summary: 目前仅作为测试使用，并未设置功能
Home-page: https://github.com/
Author: 2Or3InTheMorning
Author-email: ponsekika@gmail.com
License: UNKNOWN
Platform: UNKNOWN
Classifier: Programming Language :: Python :: 3
Classifier: License :: OSI Approved :: MIT License
Classifier: Operating System :: OS Independent
Requires-Python: >=3.6
